<?xml version="1.0" encoding="UTF-8" ?>
<!DOCTYPE struts PUBLIC 
	"-//Apache Software Foundation//DTD Struts Configuration 2.5//EN" 
	"http://struts.apache.org/dtds/struts-2.5.dtd">
<struts>
	<!-- package -->
	<package name="basePackage" extends="struts-default" abstract="true">
	<!-- ================================================定义全局处理=============================================== -->
		<!-- 全局异常处理 -->
		<global-exception-mappings>
		    <exception-mapping result="exceptionError" exception="java.lang.NullPointerException" />
		    <exception-mapping result="exceptionError" exception="java.lang.NoSuchMethodException" />
		    <exception-mapping result="exceptionError" exception="java.lang.Exception" />
		</global-exception-mappings>
	</package>
	<include file="config/struts/struts_main.xml"></include>
	<!-- ================================================参数配置======================================== -->
	<constant name="struts.enable.SlashesInActionNames" value="true"/>
    <constant name="struts.mapper.alwaysSelectFullNamespace" value="false"/>
	<constant name="struts.configuration.xml.reload" value="true" />
	<constant name="struts.multipart.maxSize" value="500000000" />
	<constant name="struts.action.extension" value=",action,do"/>
</struts>